{
  "schemaVersion": 1,
  "versionCode": 41,
  "versionName": "0.14.0-beta.6",
  "minSupportedVersionCode": 31,
  "publishedAt": "2026-07-20T07:31:16Z",
  "mandatory": false,
  "releasePageUrl": "https://github.com/SolasWyrd/AutoDiagOBD-Releases/releases/tag/v0.14.0-beta.6",
  "apk": {
    "url": "https://github.com/SolasWyrd/AutoDiagOBD-Releases/releases/download/v0.14.0-beta.6/AutoDiag-0.14.0-beta.6-build41-release.apk",
    "size": 1908087,
    "sha256": "e292288ccf33869b13a578653fefc6199ae9bfef0c2bdad2f00a985a1b049130"
  },
  "changelog": [
    "Редактор автомобиля использует зависимые списки с поиском вместо свободного ввода.",
    "Марки и модели легковых автомобилей загружаются из официального каталога NHTSA vPIC.",
    "Для LADA Priora и Vesta добавлены проверенные конфигурации из официальных материалов LADA.",
    "Код двигателя, калибровка и прошивка ЭБУ больше не вводятся вручную.",
    "Добавлены фиксированные списки топлива, поколения ГБО и марки контроллера.",
    "Редактор сохраняет кнопки действий доступными при крупном системном тексте."
  ]
}
